{
   "ContextClassName": "Vityaz_MSCRMContext",
   "ContextNamespace": null,
   "DefaultDacpacSchema": null,
   "FilterSchemas": false,
   "IncludeConnectionString": true,
   "ModelNamespace": null,
   "OutputContextPath": "ReportContext",
   "OutputPath": "ReportBaseModels",
   "ProjectRootNamespace": "ReportsCore",
   "Schemas": null,
   "SelectedHandlebarsLanguage": 0,
   "SelectedToBeGenerated": 0,
   "Tables": [
      {
         "HasPrimaryKey": true,
         "Name": "[dbo].[Reports]"
      },
      {
         "HasPrimaryKey": true,
         "Name": "[dbo].[UsersReports]"
      }
   ],
   "UseDatabaseNames": false,
   "UseDbContextSplitting": false,
   "UseFluentApiOnly": false,
   "UseHandleBars": false,
   "UseInflector": false,
   "UseLegacyPluralizer": false,
   "UseNodaTime": false,
   "UseSpatial": false,
   "UseStoredProcedures": false
}